{
  "makima": [
    {
      "id": 573911692,
      "name": "trezhywinks",
      "caregoria": "cosplay",
      "autor": "makima",
      "text": "Makima Cosplay",
      "creator": "https://github.com/trezhywinks",
      "github": "https://github.com/trezhywinks/API-Makima/",
      "imagem": "https://raw.githubusercontent.com/trezhywinks/API-Makima/main/IMG_4599.jpeg",
      "date": "2026-02-11"
    },
    {
      "id": 386419737,
      "name": "trezhywinks",
      "caregoria": "cosplay",
      "autor": "makima",
      "text": "Makima Cosplay",
      "creator": "https://github.com/trezhywinks",
      "github": "https://github.com/trezhywinks/API-Makima/",
      "imagem": "https://raw.githubusercontent.com/trezhywinks/API-Makima/main/IMG_4737.jpeg",
      "date": "2026-02-11"
    },
    {
      "id": 150444856,
      "name": "trezhywinks",
      "caregoria": "cosplay",
      "autor": "makima",
      "text": "Makima Cosplay",
      "creator": "https://github.com/trezhywinks",
      "github": "https://github.com/trezhywinks/API-Makima/",
      "imagem": "https://raw.githubusercontent.com/trezhywinks/API-Makima/main/IMG_4759.jpeg",
      "date": "2026-02-11"
    },
    {
      "id": 637930006,
      "name": "trezhywinks",
      "caregoria": "cosplay",
      "autor": "makima",
      "text": "Makima Cosplay",
      "creator": "https://github.com/trezhywinks",
      "github": "https://github.com/trezhywinks/API-Makima/",
      "imagem": "https://raw.githubusercontent.com/trezhywinks/API-Makima/main/IMG_4760.jpeg",
      "date": "2026-02-11"
    },
    {
      "id": 843348984,
      "name": "trezhywinks",
      "caregoria": "cosplay",
      "autor": "makima",
      "text": "Makima Cosplay",
      "creator": "https://github.com/trezhywinks",
      "github": "https://github.com/trezhywinks/API-Makima/",
      "imagem": "https://raw.githubusercontent.com/trezhywinks/API-Makima/main/IMG_4761.jpeg",
      "date": "2026-02-11"
    },
    {
      "id": 535018817,
      "name": "trezhywinks",
      "caregoria": "cosplay",
      "autor": "makima",
      "text": "Makima Cosplay",
      "creator": "https://github.com/trezhywinks",
      "github": "https://github.com/trezhywinks/API-Makima/",
      "imagem": "https://raw.githubusercontent.com/trezhywinks/API-Makima/main/IMG_4796.jpeg",
      "date": "2026-02-11"
    },
    {
      "id": 667632990,
      "name": "trezhywinks",
      "caregoria": "cosplay",
      "autor": "makima",
      "text": "Makima Cosplay",
      "creator": "https://github.com/trezhywinks",
      "github": "https://github.com/trezhywinks/API-Makima/",
      "imagem": "https://raw.githubusercontent.com/trezhywinks/API-Makima/main/IMG_4797.jpeg",
      "date": "2026-02-11"
    },
    {
      "id": 891487726,
      "name": "trezhywinks",
      "caregoria": "cosplay",
      "autor": "makima",
      "text": "Makima Cosplay",
      "creator": "https://github.com/trezhywinks",
      "github": "https://github.com/trezhywinks/API-Makima/",
      "imagem": "https://raw.githubusercontent.com/trezhywinks/API-Makima/main/IMG_4803.jpeg",
      "date": "2026-02-11"
    },
    {
      "id": 543310034,
      "name": "trezhywinks",
      "caregoria": "cosplay",
      "autor": "makima",
      "text": "Makima Cosplay",
      "creator": "https://github.com/trezhywinks",
      "github": "https://github.com/trezhywinks/API-Makima/",
      "imagem": "https://raw.githubusercontent.com/trezhywinks/API-Makima/main/IMG_4851.jpeg",
      "date": "2026-02-11"
    },
    {
      "id": 258023074,
      "name": "trezhywinks",
      "caregoria": "cosplay",
      "autor": "makima",
      "text": "Makima Cosplay",
      "creator": "https://github.com/trezhywinks",
      "github": "https://github.com/trezhywinks/API-Makima/",
      "imagem": "https://raw.githubusercontent.com/trezhywinks/API-Makima/main/IMG_4895.jpeg",
      "date": "2026-02-11"
    },
    {
      "id": 999882681,
      "name": "trezhywinks",
      "caregoria": "cosplay",
      "autor": "makima",
      "text": "Makima Cosplay",
      "creator": "https://github.com/trezhywinks",
      "github": "https://github.com/trezhywinks/API-Makima/",
      "imagem": "https://raw.githubusercontent.com/trezhywinks/API-Makima/main/IMG_4896.jpeg",
      "date": "2026-02-11"
    },
    {
      "id": 133738711,
      "name": "trezhywinks",
      "caregoria": "cosplay",
      "autor": "makima",
      "text": "Makima Cosplay",
      "creator": "https://github.com/trezhywinks",
      "github": "https://github.com/trezhywinks/API-Makima/",
      "imagem": "https://raw.githubusercontent.com/trezhywinks/API-Makima/main/IMG_4897.jpeg",
      "date": "2026-02-11"
    },
    {
      "id": 732924553,
      "name": "trezhywinks",
      "caregoria": "cosplay",
      "autor": "makima",
      "text": "Makima Cosplay",
      "creator": "https://github.com/trezhywinks",
      "github": "https://github.com/trezhywinks/API-Makima/",
      "imagem": "https://raw.githubusercontent.com/trezhywinks/API-Makima/main/IMG_4898.jpeg",
      "date": "2026-02-11"
    },
    {
      "id": 292179383,
      "name": "trezhywinks",
      "caregoria": "cosplay",
      "autor": "makima",
      "text": "Makima Cosplay",
      "creator": "https://github.com/trezhywinks",
      "github": "https://github.com/trezhywinks/API-Makima/",
      "imagem": "https://raw.githubusercontent.com/trezhywinks/API-Makima/main/IMG_4901.jpeg",
      "date": "2026-02-11"
    },
    {
      "id": 356806747,
      "name": "trezhywinks",
      "caregoria": "cosplay",
      "autor": "makima",
      "text": "Makima Cosplay",
      "creator": "https://github.com/trezhywinks",
      "github": "https://github.com/trezhywinks/API-Makima/",
      "imagem": "https://raw.githubusercontent.com/trezhywinks/API-Makima/main/IMG_4902.jpeg",
      "date": "2026-02-11"
    },
    {
      "id": 720785726,
      "name": "trezhywinks",
      "caregoria": "cosplay",
      "autor": "makima",
      "text": "Makima Cosplay",
      "creator": "https://github.com/trezhywinks",
      "github": "https://github.com/trezhywinks/API-Makima/",
      "imagem": "https://raw.githubusercontent.com/trezhywinks/API-Makima/main/IMG_4903.jpeg",
      "date": "2026-02-11"
    },
    {
      "id": 568608254,
      "name": "trezhywinks",
      "caregoria": "cosplay",
      "autor": "makima",
      "text": "Makima Cosplay",
      "creator": "https://github.com/trezhywinks",
      "github": "https://github.com/trezhywinks/API-Makima/",
      "imagem": "https://raw.githubusercontent.com/trezhywinks/API-Makima/main/IMG_4904.jpeg",
      "date": "2026-02-11"
    },
    {
      "id": 243809611,
      "name": "trezhywinks",
      "caregoria": "cosplay",
      "autor": "makima",
      "text": "Makima Cosplay",
      "creator": "https://github.com/trezhywinks",
      "github": "https://github.com/trezhywinks/API-Makima/",
      "imagem": "https://raw.githubusercontent.com/trezhywinks/API-Makima/main/IMG_4905.jpeg",
      "date": "2026-02-11"
    },
    {
      "id": 837169492,
      "name": "trezhywinks",
      "caregoria": "cosplay",
      "autor": "makima",
      "text": "Makima Cosplay",
      "creator": "https://github.com/trezhywinks",
      "github": "https://github.com/trezhywinks/API-Makima/",
      "imagem": "https://raw.githubusercontent.com/trezhywinks/API-Makima/main/IMG_4906.jpeg",
      "date": "2026-02-11"
    },
    {
      "id": 233086355,
      "name": "trezhywinks",
      "caregoria": "cosplay",
      "autor": "makima",
      "text": "Makima Cosplay",
      "creator": "https://github.com/trezhywinks",
      "github": "https://github.com/trezhywinks/API-Makima/",
      "imagem": "https://raw.githubusercontent.com/trezhywinks/API-Makima/main/IMG_4907.jpeg",
      "date": "2026-02-11"
    },
    {
      "id": 666141556,
      "name": "trezhywinks",
      "caregoria": "cosplay",
      "autor": "makima",
      "text": "Makima Cosplay",
      "creator": "https://github.com/trezhywinks",
      "github": "https://github.com/trezhywinks/API-Makima/",
      "imagem": "https://raw.githubusercontent.com/trezhywinks/API-Makima/main/IMG_4908.jpeg",
      "date": "2026-02-11"
    },
    {
      "id": 657022094,
      "name": "trezhywinks",
      "caregoria": "cosplay",
      "autor": "makima",
      "text": "Makima Cosplay",
      "creator": "https://github.com/trezhywinks",
      "github": "https://github.com/trezhywinks/API-Makima/",
      "imagem": "https://raw.githubusercontent.com/trezhywinks/API-Makima/main/IMG_4909.jpeg",
      "date": "2026-02-11"
    },
    {
      "id": 659573312,
      "name": "trezhywinks",
      "caregoria": "cosplay",
      "autor": "makima",
      "text": "Makima Cosplay",
      "creator": "https://github.com/trezhywinks",
      "github": "https://github.com/trezhywinks/API-Makima/",
      "imagem": "https://raw.githubusercontent.com/trezhywinks/API-Makima/main/IMG_4910.jpeg",
      "date": "2026-02-11"
    },
    {
      "id": 101735350,
      "name": "trezhywinks",
      "caregoria": "cosplay",
      "autor": "makima",
      "text": "Makima Cosplay",
      "creator": "https://github.com/trezhywinks",
      "github": "https://github.com/trezhywinks/API-Makima/",
      "imagem": "https://raw.githubusercontent.com/trezhywinks/API-Makima/main/IMG_4911.jpeg",
      "date": "2026-02-11"
    },
    {
      "id": 797198552,
      "name": "trezhywinks",
      "caregoria": "cosplay",
      "autor": "makima",
      "text": "Makima Cosplay",
      "creator": "https://github.com/trezhywinks",
      "github": "https://github.com/trezhywinks/API-Makima/",
      "imagem": "https://raw.githubusercontent.com/trezhywinks/API-Makima/main/IMG_4912.jpeg",
      "date": "2026-02-11"
    },
    {
      "id": 609939866,
      "name": "trezhywinks",
      "caregoria": "cosplay",
      "autor": "makima",
      "text": "Makima Cosplay",
      "creator": "https://github.com/trezhywinks",
      "github": "https://github.com/trezhywinks/API-Makima/",
      "imagem": "https://raw.githubusercontent.com/trezhywinks/API-Makima/main/IMG_4913.jpeg",
      "date": "2026-02-11"
    },
    {
      "id": 672589248,
      "name": "trezhywinks",
      "caregoria": "cosplay",
      "autor": "makima",
      "text": "Makima Cosplay",
      "creator": "https://github.com/trezhywinks",
      "github": "https://github.com/trezhywinks/API-Makima/",
      "imagem": "https://raw.githubusercontent.com/trezhywinks/API-Makima/main/IMG_4914.jpeg",
      "date": "2026-02-11"
    },
    {
      "id": 196100321,
      "name": "trezhywinks",
      "caregoria": "cosplay",
      "autor": "makima",
      "text": "Makima Cosplay",
      "creator": "https://github.com/trezhywinks",
      "github": "https://github.com/trezhywinks/API-Makima/",
      "imagem": "https://raw.githubusercontent.com/trezhywinks/API-Makima/main/IMG_4915.jpeg",
      "date": "2026-02-11"
    },
    {
      "id": 948854908,
      "name": "trezhywinks",
      "caregoria": "cosplay",
      "autor": "makima",
      "text": "Makima Cosplay",
      "creator": "https://github.com/trezhywinks",
      "github": "https://github.com/trezhywinks/API-Makima/",
      "imagem": "https://raw.githubusercontent.com/trezhywinks/API-Makima/main/IMG_4916.jpeg",
      "date": "2026-02-11"
    },
    {
      "id": 150750175,
      "name": "trezhywinks",
      "caregoria": "cosplay",
      "autor": "makima",
      "text": "Makima Cosplay",
      "creator": "https://github.com/trezhywinks",
      "github": "https://github.com/trezhywinks/API-Makima/",
      "imagem": "https://raw.githubusercontent.com/trezhywinks/API-Makima/main/IMG_4917.jpeg",
      "date": "2026-02-11"
    },
    {
      "id": 238700932,
      "name": "trezhywinks",
      "caregoria": "cosplay",
      "autor": "makima",
      "text": "Makima Cosplay",
      "creator": "https://github.com/trezhywinks",
      "github": "https://github.com/trezhywinks/API-Makima/",
      "imagem": "https://raw.githubusercontent.com/trezhywinks/API-Makima/main/IMG_4918.jpeg",
      "date": "2026-02-11"
    },
    {
      "id": 724066838,
      "name": "trezhywinks",
      "caregoria": "cosplay",
      "autor": "makima",
      "text": "Makima Cosplay",
      "creator": "https://github.com/trezhywinks",
      "github": "https://github.com/trezhywinks/API-Makima/",
      "imagem": "https://raw.githubusercontent.com/trezhywinks/API-Makima/main/IMG_4919.jpeg",
      "date": "2026-02-11"
    },
    {
      "id": 451787483,
      "name": "trezhywinks",
      "caregoria": "cosplay",
      "autor": "makima",
      "text": "Makima Cosplay",
      "creator": "https://github.com/trezhywinks",
      "github": "https://github.com/trezhywinks/API-Makima/",
      "imagem": "https://raw.githubusercontent.com/trezhywinks/API-Makima/main/IMG_4920.jpeg",
      "date": "2026-02-11"
    },
    {
      "id": 979181550,
      "name": "trezhywinks",
      "caregoria": "cosplay",
      "autor": "makima",
      "text": "Makima Cosplay",
      "creator": "https://github.com/trezhywinks",
      "github": "https://github.com/trezhywinks/API-Makima/",
      "imagem": "https://raw.githubusercontent.com/trezhywinks/API-Makima/main/IMG_4921.jpeg",
      "date": "2026-02-11"
    },
    {
      "id": 329937771,
      "name": "trezhywinks",
      "caregoria": "cosplay",
      "autor": "makima",
      "text": "Makima Cosplay",
      "creator": "https://github.com/trezhywinks",
      "github": "https://github.com/trezhywinks/API-Makima/",
      "imagem": "https://raw.githubusercontent.com/trezhywinks/API-Makima/main/IMG_4922.jpeg",
      "date": "2026-02-11"
    },
    {
      "id": 879109945,
      "name": "trezhywinks",
      "caregoria": "cosplay",
      "autor": "makima",
      "text": "Makima Cosplay",
      "creator": "https://github.com/trezhywinks",
      "github": "https://github.com/trezhywinks/API-Makima/",
      "imagem": "https://raw.githubusercontent.com/trezhywinks/API-Makima/main/IMG_4923.jpeg",
      "date": "2026-02-11"
    },
    {
      "id": 953489628,
      "name": "trezhywinks",
      "caregoria": "cosplay",
      "autor": "makima",
      "text": "Makima Cosplay",
      "creator": "https://github.com/trezhywinks",
      "github": "https://github.com/trezhywinks/API-Makima/",
      "imagem": "https://raw.githubusercontent.com/trezhywinks/API-Makima/main/IMG_4924.jpeg",
      "date": "2026-02-11"
    },
    {
      "id": 889299177,
      "name": "trezhywinks",
      "caregoria": "cosplay",
      "autor": "makima",
      "text": "Makima Cosplay",
      "creator": "https://github.com/trezhywinks",
      "github": "https://github.com/trezhywinks/API-Makima/",
      "imagem": "https://raw.githubusercontent.com/trezhywinks/API-Makima/main/IMG_4925.jpeg",
      "date": "2026-02-11"
    },
    {
      "id": 149826921,
      "name": "trezhywinks",
      "caregoria": "cosplay",
      "autor": "makima",
      "text": "Makima Cosplay",
      "creator": "https://github.com/trezhywinks",
      "github": "https://github.com/trezhywinks/API-Makima/",
      "imagem": "https://raw.githubusercontent.com/trezhywinks/API-Makima/main/IMG_4926.jpeg",
      "date": "2026-02-11"
    },
    {
      "id": 771384586,
      "name": "trezhywinks",
      "caregoria": "cosplay",
      "autor": "makima",
      "text": "Makima Cosplay",
      "creator": "https://github.com/trezhywinks",
      "github": "https://github.com/trezhywinks/API-Makima/",
      "imagem": "https://raw.githubusercontent.com/trezhywinks/API-Makima/main/IMG_4927.jpeg",
      "date": "2026-02-11"
    },
    {
      "id": 519599403,
      "name": "trezhywinks",
      "caregoria": "cosplay",
      "autor": "makima",
      "text": "Makima Cosplay",
      "creator": "https://github.com/trezhywinks",
      "github": "https://github.com/trezhywinks/API-Makima/",
      "imagem": "https://raw.githubusercontent.com/trezhywinks/API-Makima/main/IMG_4928.jpeg",
      "date": "2026-02-11"
    },
    {
      "id": 933341046,
      "name": "trezhywinks",
      "caregoria": "cosplay",
      "autor": "makima",
      "text": "Makima Cosplay",
      "creator": "https://github.com/trezhywinks",
      "github": "https://github.com/trezhywinks/API-Makima/",
      "imagem": "https://raw.githubusercontent.com/trezhywinks/API-Makima/main/IMG_4929.jpeg",
      "date": "2026-02-11"
    },
    {
      "id": 103163826,
      "name": "trezhywinks",
      "caregoria": "cosplay",
      "autor": "makima",
      "text": "Makima Cosplay",
      "creator": "https://github.com/trezhywinks",
      "github": "https://github.com/trezhywinks/API-Makima/",
      "imagem": "https://raw.githubusercontent.com/trezhywinks/API-Makima/main/IMG_4930.jpeg",
      "date": "2026-02-11"
    },
    {
      "id": 220589125,
      "name": "trezhywinks",
      "caregoria": "cosplay",
      "autor": "makima",
      "text": "Makima Cosplay",
      "creator": "https://github.com/trezhywinks",
      "github": "https://github.com/trezhywinks/API-Makima/",
      "imagem": "https://raw.githubusercontent.com/trezhywinks/API-Makima/main/IMG_4931.jpeg",
      "date": "2026-02-11"
    },
    {
      "id": 364486075,
      "name": "trezhywinks",
      "caregoria": "cosplay",
      "autor": "makima",
      "text": "Makima Cosplay",
      "creator": "https://github.com/trezhywinks",
      "github": "https://github.com/trezhywinks/API-Makima/",
      "imagem": "https://raw.githubusercontent.com/trezhywinks/API-Makima/main/IMG_4932.jpeg",
      "date": "2026-02-11"
    },
    {
      "id": 815230354,
      "name": "trezhywinks",
      "caregoria": "cosplay",
      "autor": "makima",
      "text": "Makima Cosplay",
      "creator": "https://github.com/trezhywinks",
      "github": "https://github.com/trezhywinks/API-Makima/",
      "imagem": "https://raw.githubusercontent.com/trezhywinks/API-Makima/main/IMG_4933.jpeg",
      "date": "2026-02-11"
    },
    {
      "id": 920373831,
      "name": "trezhywinks",
      "caregoria": "cosplay",
      "autor": "makima",
      "text": "Makima Cosplay",
      "creator": "https://github.com/trezhywinks",
      "github": "https://github.com/trezhywinks/API-Makima/",
      "imagem": "https://raw.githubusercontent.com/trezhywinks/API-Makima/main/IMG_4934.jpeg",
      "date": "2026-02-11"
    },
    {
      "id": 276140378,
      "name": "trezhywinks",
      "caregoria": "cosplay",
      "autor": "makima",
      "text": "Makima Cosplay",
      "creator": "https://github.com/trezhywinks",
      "github": "https://github.com/trezhywinks/API-Makima/",
      "imagem": "https://raw.githubusercontent.com/trezhywinks/API-Makima/main/IMG_4935.jpeg",
      "date": "2026-02-11"
    },
    {
      "id": 556610290,
      "name": "trezhywinks",
      "caregoria": "cosplay",
      "autor": "makima",
      "text": "Makima Cosplay",
      "creator": "https://github.com/trezhywinks",
      "github": "https://github.com/trezhywinks/API-Makima/",
      "imagem": "https://raw.githubusercontent.com/trezhywinks/API-Makima/main/IMG_4936.jpeg",
      "date": "2026-02-11"
    },
    {
      "id": 792563438,
      "name": "trezhywinks",
      "caregoria": "cosplay",
      "autor": "makima",
      "text": "Makima Cosplay",
      "creator": "https://github.com/trezhywinks",
      "github": "https://github.com/trezhywinks/API-Makima/",
      "imagem": "https://raw.githubusercontent.com/trezhywinks/API-Makima/main/IMG_4937.jpeg",
      "date": "2026-02-11"
    },
    {
      "id": 497885509,
      "name": "trezhywinks",
      "caregoria": "cosplay",
      "autor": "makima",
      "text": "Makima Cosplay",
      "creator": "https://github.com/trezhywinks",
      "github": "https://github.com/trezhywinks/API-Makima/",
      "imagem": "https://raw.githubusercontent.com/trezhywinks/API-Makima/main/IMG_4938.jpeg",
      "date": "2026-02-11"
    },
    {
      "id": 932922826,
      "name": "trezhywinks",
      "caregoria": "cosplay",
      "autor": "makima",
      "text": "Makima Cosplay",
      "creator": "https://github.com/trezhywinks",
      "github": "https://github.com/trezhywinks/API-Makima/",
      "imagem": "https://raw.githubusercontent.com/trezhywinks/API-Makima/main/IMG_4939.jpeg",
      "date": "2026-02-11"
    },
    {
      "id": 630747523,
      "name": "trezhywinks",
      "caregoria": "cosplay",
      "autor": "makima",
      "text": "Makima Cosplay",
      "creator": "https://github.com/trezhywinks",
      "github": "https://github.com/trezhywinks/API-Makima/",
      "imagem": "https://raw.githubusercontent.com/trezhywinks/API-Makima/main/IMG_4940.jpeg",
      "date": "2026-02-11"
    },
    {
      "id": 622728054,
      "name": "trezhywinks",
      "caregoria": "cosplay",
      "autor": "makima",
      "text": "Makima Cosplay",
      "creator": "https://github.com/trezhywinks",
      "github": "https://github.com/trezhywinks/API-Makima/",
      "imagem": "https://raw.githubusercontent.com/trezhywinks/API-Makima/main/IMG_4941.jpeg",
      "date": "2026-02-11"
    },
    {
      "id": 552481033,
      "name": "trezhywinks",
      "caregoria": "cosplay",
      "autor": "makima",
      "text": "Makima Cosplay",
      "creator": "https://github.com/trezhywinks",
      "github": "https://github.com/trezhywinks/API-Makima/",
      "imagem": "https://raw.githubusercontent.com/trezhywinks/API-Makima/main/IMG_4942.jpeg",
      "date": "2026-02-11"
    },
    {
      "id": 650257088,
      "name": "trezhywinks",
      "caregoria": "cosplay",
      "autor": "makima",
      "text": "Makima Cosplay",
      "creator": "https://github.com/trezhywinks",
      "github": "https://github.com/trezhywinks/API-Makima/",
      "imagem": "https://raw.githubusercontent.com/trezhywinks/API-Makima/main/IMG_4943.jpeg",
      "date": "2026-02-11"
    },
    {
      "id": 977058324,
      "name": "trezhywinks",
      "caregoria": "cosplay",
      "autor": "makima",
      "text": "Makima Cosplay",
      "creator": "https://github.com/trezhywinks",
      "github": "https://github.com/trezhywinks/API-Makima/",
      "imagem": "https://raw.githubusercontent.com/trezhywinks/API-Makima/main/IMG_4944.jpeg",
      "date": "2026-02-11"
    },
    {
      "id": 711300764,
      "name": "trezhywinks",
      "caregoria": "cosplay",
      "autor": "makima",
      "text": "Makima Cosplay",
      "creator": "https://github.com/trezhywinks",
      "github": "https://github.com/trezhywinks/API-Makima/",
      "imagem": "https://raw.githubusercontent.com/trezhywinks/API-Makima/main/IMG_4945.jpeg",
      "date": "2026-02-11"
    },
    {
      "id": 844767844,
      "name": "trezhywinks",
      "caregoria": "cosplay",
      "autor": "makima",
      "text": "Makima Cosplay",
      "creator": "https://github.com/trezhywinks",
      "github": "https://github.com/trezhywinks/API-Makima/",
      "imagem": "https://raw.githubusercontent.com/trezhywinks/API-Makima/main/IMG_4946.jpeg",
      "date": "2026-02-11"
    },
    {
      "id": 251575515,
      "name": "trezhywinks",
      "caregoria": "cosplay",
      "autor": "makima",
      "text": "Makima Cosplay",
      "creator": "https://github.com/trezhywinks",
      "github": "https://github.com/trezhywinks/API-Makima/",
      "imagem": "https://raw.githubusercontent.com/trezhywinks/API-Makima/main/IMG_4947.jpeg",
      "date": "2026-02-11"
    },
    {
      "id": 393713016,
      "name": "trezhywinks",
      "caregoria": "cosplay",
      "autor": "makima",
      "text": "Makima Cosplay",
      "creator": "https://github.com/trezhywinks",
      "github": "https://github.com/trezhywinks/API-Makima/",
      "imagem": "https://raw.githubusercontent.com/trezhywinks/API-Makima/main/IMG_4948.jpeg",
      "date": "2026-02-11"
    },
    {
      "id": 497494548,
      "name": "trezhywinks",
      "caregoria": "cosplay",
      "autor": "makima",
      "text": "Makima Cosplay",
      "creator": "https://github.com/trezhywinks",
      "github": "https://github.com/trezhywinks/API-Makima/",
      "imagem": "https://raw.githubusercontent.com/trezhywinks/API-Makima/main/IMG_4949.jpeg",
      "date": "2026-02-11"
    },
    {
      "id": 334354382,
      "name": "trezhywinks",
      "caregoria": "cosplay",
      "autor": "makima",
      "text": "Makima Cosplay",
      "creator": "https://github.com/trezhywinks",
      "github": "https://github.com/trezhywinks/API-Makima/",
      "imagem": "https://raw.githubusercontent.com/trezhywinks/API-Makima/main/IMG_4950.jpeg",
      "date": "2026-02-11"
    },
    {
      "id": 295955116,
      "name": "trezhywinks",
      "caregoria": "cosplay",
      "autor": "makima",
      "text": "Makima Cosplay",
      "creator": "https://github.com/trezhywinks",
      "github": "https://github.com/trezhywinks/API-Makima/",
      "imagem": "https://raw.githubusercontent.com/trezhywinks/API-Makima/main/IMG_4951.jpeg",
      "date": "2026-02-11"
    },
    {
      "id": 500720545,
      "name": "trezhywinks",
      "caregoria": "cosplay",
      "autor": "makima",
      "text": "Makima Cosplay",
      "creator": "https://github.com/trezhywinks",
      "github": "https://github.com/trezhywinks/API-Makima/",
      "imagem": "https://raw.githubusercontent.com/trezhywinks/API-Makima/main/IMG_4952.jpeg",
      "date": "2026-02-11"
    },
    {
      "id": 750121078,
      "name": "trezhywinks",
      "caregoria": "cosplay",
      "autor": "makima",
      "text": "Makima Cosplay",
      "creator": "https://github.com/trezhywinks",
      "github": "https://github.com/trezhywinks/API-Makima/",
      "imagem": "https://raw.githubusercontent.com/trezhywinks/API-Makima/main/IMG_4953.jpeg",
      "date": "2026-02-11"
    },
    {
      "id": 165544205,
      "name": "trezhywinks",
      "caregoria": "cosplay",
      "autor": "makima",
      "text": "Makima Cosplay",
      "creator": "https://github.com/trezhywinks",
      "github": "https://github.com/trezhywinks/API-Makima/",
      "imagem": "https://raw.githubusercontent.com/trezhywinks/API-Makima/main/IMG_4954.jpeg",
      "date": "2026-02-11"
    },
    {
      "id": 214820541,
      "name": "trezhywinks",
      "caregoria": "cosplay",
      "autor": "makima",
      "text": "Makima Cosplay",
      "creator": "https://github.com/trezhywinks",
      "github": "https://github.com/trezhywinks/API-Makima/",
      "imagem": "https://raw.githubusercontent.com/trezhywinks/API-Makima/main/IMG_4955.jpeg",
      "date": "2026-02-11"
    },
    {
      "id": 956497899,
      "name": "trezhywinks",
      "caregoria": "cosplay",
      "autor": "makima",
      "text": "Makima Cosplay",
      "creator": "https://github.com/trezhywinks",
      "github": "https://github.com/trezhywinks/API-Makima/",
      "imagem": "https://raw.githubusercontent.com/trezhywinks/API-Makima/main/IMG_4956.jpeg",
      "date": "2026-02-11"
    },
    {
      "id": 548767524,
      "name": "trezhywinks",
      "caregoria": "cosplay",
      "autor": "makima",
      "text": "Makima Cosplay",
      "creator": "https://github.com/trezhywinks",
      "github": "https://github.com/trezhywinks/API-Makima/",
      "imagem": "https://raw.githubusercontent.com/trezhywinks/API-Makima/main/IMG_4957.jpeg",
      "date": "2026-02-11"
    },
    {
      "id": 364562357,
      "name": "trezhywinks",
      "caregoria": "cosplay",
      "autor": "makima",
      "text": "Makima Cosplay",
      "creator": "https://github.com/trezhywinks",
      "github": "https://github.com/trezhywinks/API-Makima/",
      "imagem": "https://raw.githubusercontent.com/trezhywinks/API-Makima/main/IMG_4958.jpeg",
      "date": "2026-02-11"
    },
    {
      "id": 644949468,
      "name": "trezhywinks",
      "caregoria": "cosplay",
      "autor": "makima",
      "text": "Makima Cosplay",
      "creator": "https://github.com/trezhywinks",
      "github": "https://github.com/trezhywinks/API-Makima/",
      "imagem": "https://raw.githubusercontent.com/trezhywinks/API-Makima/main/IMG_4959.jpeg",
      "date": "2026-02-11"
    },
    {
      "id": 502894244,
      "name": "trezhywinks",
      "caregoria": "cosplay",
      "autor": "makima",
      "text": "Makima Cosplay",
      "creator": "https://github.com/trezhywinks",
      "github": "https://github.com/trezhywinks/API-Makima/",
      "imagem": "https://raw.githubusercontent.com/trezhywinks/API-Makima/main/IMG_4960.jpeg",
      "date": "2026-02-11"
    },
    {
      "id": 259082296,
      "name": "trezhywinks",
      "caregoria": "cosplay",
      "autor": "makima",
      "text": "Makima Cosplay",
      "creator": "https://github.com/trezhywinks",
      "github": "https://github.com/trezhywinks/API-Makima/",
      "imagem": "https://raw.githubusercontent.com/trezhywinks/API-Makima/main/IMG_4961.jpeg",
      "date": "2026-02-11"
    },
    {
      "id": 955808255,
      "name": "trezhywinks",
      "caregoria": "cosplay",
      "autor": "makima",
      "text": "Makima Cosplay",
      "creator": "https://github.com/trezhywinks",
      "github": "https://github.com/trezhywinks/API-Makima/",
      "imagem": "https://raw.githubusercontent.com/trezhywinks/API-Makima/main/IMG_4962.jpeg",
      "date": "2026-02-11"
    },
    {
      "id": 860796173,
      "name": "trezhywinks",
      "caregoria": "cosplay",
      "autor": "makima",
      "text": "Makima Cosplay",
      "creator": "https://github.com/trezhywinks",
      "github": "https://github.com/trezhywinks/API-Makima/",
      "imagem": "https://raw.githubusercontent.com/trezhywinks/API-Makima/main/IMG_4963.jpeg",
      "date": "2026-02-11"
    },
    {
      "id": 647400979,
      "name": "trezhywinks",
      "caregoria": "cosplay",
      "autor": "makima",
      "text": "Makima Cosplay",
      "creator": "https://github.com/trezhywinks",
      "github": "https://github.com/trezhywinks/API-Makima/",
      "imagem": "https://raw.githubusercontent.com/trezhywinks/API-Makima/main/IMG_4964.jpeg",
      "date": "2026-02-11"
    },
    {
      "id": 633349430,
      "name": "trezhywinks",
      "caregoria": "cosplay",
      "autor": "makima",
      "text": "Makima Cosplay",
      "creator": "https://github.com/trezhywinks",
      "github": "https://github.com/trezhywinks/API-Makima/",
      "imagem": "https://raw.githubusercontent.com/trezhywinks/API-Makima/main/IMG_4965.jpeg",
      "date": "2026-02-11"
    },
    {
      "id": 876235471,
      "name": "trezhywinks",
      "caregoria": "cosplay",
      "autor": "makima",
      "text": "Makima Cosplay",
      "creator": "https://github.com/trezhywinks",
      "github": "https://github.com/trezhywinks/API-Makima/",
      "imagem": "https://raw.githubusercontent.com/trezhywinks/API-Makima/main/IMG_4966.jpeg",
      "date": "2026-02-11"
    },
    {
      "id": 530369486,
      "name": "trezhywinks",
      "caregoria": "cosplay",
      "autor": "makima",
      "text": "Makima Cosplay",
      "creator": "https://github.com/trezhywinks",
      "github": "https://github.com/trezhywinks/API-Makima/",
      "imagem": "https://raw.githubusercontent.com/trezhywinks/API-Makima/main/IMG_4967.jpeg",
      "date": "2026-02-11"
    },
    {
      "id": 536907169,
      "name": "trezhywinks",
      "caregoria": "cosplay",
      "autor": "makima",
      "text": "Makima Cosplay",
      "creator": "https://github.com/trezhywinks",
      "github": "https://github.com/trezhywinks/API-Makima/",
      "imagem": "https://raw.githubusercontent.com/trezhywinks/API-Makima/main/IMG_4968.jpeg",
      "date": "2026-02-11"
    },
    {
      "id": 537311296,
      "name": "trezhywinks",
      "caregoria": "cosplay",
      "autor": "makima",
      "text": "Makima Cosplay",
      "creator": "https://github.com/trezhywinks",
      "github": "https://github.com/trezhywinks/API-Makima/",
      "imagem": "https://raw.githubusercontent.com/trezhywinks/API-Makima/main/IMG_4969.jpeg",
      "date": "2026-02-11"
    },
    {
      "id": 450314156,
      "name": "trezhywinks",
      "caregoria": "cosplay",
      "autor": "makima",
      "text": "Makima Cosplay",
      "creator": "https://github.com/trezhywinks",
      "github": "https://github.com/trezhywinks/API-Makima/",
      "imagem": "https://raw.githubusercontent.com/trezhywinks/API-Makima/main/IMG_4970.jpeg",
      "date": "2026-02-11"
    },
    {
      "id": 457735011,
      "name": "trezhywinks",
      "caregoria": "cosplay",
      "autor": "makima",
      "text": "Makima Cosplay",
      "creator": "https://github.com/trezhywinks",
      "github": "https://github.com/trezhywinks/API-Makima/",
      "imagem": "https://raw.githubusercontent.com/trezhywinks/API-Makima/main/IMG_4971.jpeg",
      "date": "2026-02-11"
    },
    {
      "id": 947977482,
      "name": "trezhywinks",
      "caregoria": "cosplay",
      "autor": "makima",
      "text": "Makima Cosplay",
      "creator": "https://github.com/trezhywinks",
      "github": "https://github.com/trezhywinks/API-Makima/",
      "imagem": "https://raw.githubusercontent.com/trezhywinks/API-Makima/main/IMG_4972.jpeg",
      "date": "2026-02-11"
    },
    {
      "id": 479049049,
      "name": "trezhywinks",
      "caregoria": "cosplay",
      "autor": "makima",
      "text": "Makima Cosplay",
      "creator": "https://github.com/trezhywinks",
      "github": "https://github.com/trezhywinks/API-Makima/",
      "imagem": "https://raw.githubusercontent.com/trezhywinks/API-Makima/main/IMG_4973.jpeg",
      "date": "2026-02-11"
    },
    {
      "id": 375745681,
      "name": "trezhywinks",
      "caregoria": "cosplay",
      "autor": "makima",
      "text": "Makima Cosplay",
      "creator": "https://github.com/trezhywinks",
      "github": "https://github.com/trezhywinks/API-Makima/",
      "imagem": "https://raw.githubusercontent.com/trezhywinks/API-Makima/main/IMG_4975.jpeg",
      "date": "2026-02-11"
    },
    {
      "id": 684286071,
      "name": "trezhywinks",
      "caregoria": "cosplay",
      "autor": "makima",
      "text": "Makima Cosplay",
      "creator": "https://github.com/trezhywinks",
      "github": "https://github.com/trezhywinks/API-Makima/",
      "imagem": "https://raw.githubusercontent.com/trezhywinks/API-Makima/main/IMG_4976.jpeg",
      "date": "2026-02-11"
    },
    {
      "id": 823658923,
      "name": "trezhywinks",
      "caregoria": "cosplay",
      "autor": "makima",
      "text": "Makima Cosplay",
      "creator": "https://github.com/trezhywinks",
      "github": "https://github.com/trezhywinks/API-Makima/",
      "imagem": "https://raw.githubusercontent.com/trezhywinks/API-Makima/main/IMG_4977.jpeg",
      "date": "2026-02-11"
    },
    {
      "id": 411574007,
      "name": "trezhywinks",
      "caregoria": "cosplay",
      "autor": "makima",
      "text": "Makima Cosplay",
      "creator": "https://github.com/trezhywinks",
      "github": "https://github.com/trezhywinks/API-Makima/",
      "imagem": "https://raw.githubusercontent.com/trezhywinks/API-Makima/main/IMG_4978.jpeg",
      "date": "2026-02-11"
    },
    {
      "id": 315743209,
      "name": "trezhywinks",
      "caregoria": "cosplay",
      "autor": "makima",
      "text": "Makima Cosplay",
      "creator": "https://github.com/trezhywinks",
      "github": "https://github.com/trezhywinks/API-Makima/",
      "imagem": "https://raw.githubusercontent.com/trezhywinks/API-Makima/main/IMG_4979.jpeg",
      "date": "2026-02-11"
    },
    {
      "id": 260732859,
      "name": "trezhywinks",
      "caregoria": "cosplay",
      "autor": "makima",
      "text": "Makima Cosplay",
      "creator": "https://github.com/trezhywinks",
      "github": "https://github.com/trezhywinks/API-Makima/",
      "imagem": "https://raw.githubusercontent.com/trezhywinks/API-Makima/main/IMG_4980.jpeg",
      "date": "2026-02-11"
    },
    {
      "id": 567882890,
      "name": "trezhywinks",
      "caregoria": "cosplay",
      "autor": "makima",
      "text": "Makima Cosplay",
      "creator": "https://github.com/trezhywinks",
      "github": "https://github.com/trezhywinks/API-Makima/",
      "imagem": "https://raw.githubusercontent.com/trezhywinks/API-Makima/main/IMG_4981.jpeg",
      "date": "2026-02-11"
    },
    {
      "id": 863092463,
      "name": "trezhywinks",
      "caregoria": "cosplay",
      "autor": "makima",
      "text": "Makima Cosplay",
      "creator": "https://github.com/trezhywinks",
      "github": "https://github.com/trezhywinks/API-Makima/",
      "imagem": "https://raw.githubusercontent.com/trezhywinks/API-Makima/main/IMG_4982.jpeg",
      "date": "2026-02-11"
    },
    {
      "id": 545087165,
      "name": "trezhywinks",
      "caregoria": "cosplay",
      "autor": "makima",
      "text": "Makima Cosplay",
      "creator": "https://github.com/trezhywinks",
      "github": "https://github.com/trezhywinks/API-Makima/",
      "imagem": "https://raw.githubusercontent.com/trezhywinks/API-Makima/main/IMG_4983.jpeg",
      "date": "2026-02-11"
    },
    {
      "id": 483045790,
      "name": "trezhywinks",
      "caregoria": "cosplay",
      "autor": "makima",
      "text": "Makima Cosplay",
      "creator": "https://github.com/trezhywinks",
      "github": "https://github.com/trezhywinks/API-Makima/",
      "imagem": "https://raw.githubusercontent.com/trezhywinks/API-Makima/main/IMG_4984.jpeg",
      "date": "2026-02-11"
    },
    {
      "id": 470170721,
      "name": "trezhywinks",
      "caregoria": "cosplay",
      "autor": "makima",
      "text": "Makima Cosplay",
      "creator": "https://github.com/trezhywinks",
      "github": "https://github.com/trezhywinks/API-Makima/",
      "imagem": "https://raw.githubusercontent.com/trezhywinks/API-Makima/main/IMG_4985.jpeg",
      "date": "2026-02-11"
    },
    {
      "id": 199414052,
      "name": "trezhywinks",
      "caregoria": "cosplay",
      "autor": "makima",
      "text": "Makima Cosplay",
      "creator": "https://github.com/trezhywinks",
      "github": "https://github.com/trezhywinks/API-Makima/",
      "imagem": "https://raw.githubusercontent.com/trezhywinks/API-Makima/main/IMG_4986.jpeg",
      "date": "2026-02-11"
    },
    {
      "id": 351655234,
      "name": "trezhywinks",
      "caregoria": "cosplay",
      "autor": "makima",
      "text": "Makima Cosplay",
      "creator": "https://github.com/trezhywinks",
      "github": "https://github.com/trezhywinks/API-Makima/",
      "imagem": "https://raw.githubusercontent.com/trezhywinks/API-Makima/main/IMG_4987.jpeg",
      "date": "2026-02-11"
    },
    {
      "id": 725229133,
      "name": "trezhywinks",
      "caregoria": "cosplay",
      "autor": "makima",
      "text": "Makima Cosplay",
      "creator": "https://github.com/trezhywinks",
      "github": "https://github.com/trezhywinks/API-Makima/",
      "imagem": "https://raw.githubusercontent.com/trezhywinks/API-Makima/main/IMG_4988.jpeg",
      "date": "2026-02-11"
    },
    {
      "id": 714762852,
      "name": "trezhywinks",
      "caregoria": "cosplay",
      "autor": "makima",
      "text": "Makima Cosplay",
      "creator": "https://github.com/trezhywinks",
      "github": "https://github.com/trezhywinks/API-Makima/",
      "imagem": "https://raw.githubusercontent.com/trezhywinks/API-Makima/main/IMG_4989.jpeg",
      "date": "2026-02-11"
    },
    {
      "id": 147774567,
      "name": "trezhywinks",
      "caregoria": "cosplay",
      "autor": "makima",
      "text": "Makima Cosplay",
      "creator": "https://github.com/trezhywinks",
      "github": "https://github.com/trezhywinks/API-Makima/",
      "imagem": "https://raw.githubusercontent.com/trezhywinks/API-Makima/main/IMG_4990.jpeg",
      "date": "2026-02-11"
    },
    {
      "id": 437101933,
      "name": "trezhywinks",
      "caregoria": "cosplay",
      "autor": "makima",
      "text": "Makima Cosplay",
      "creator": "https://github.com/trezhywinks",
      "github": "https://github.com/trezhywinks/API-Makima/",
      "imagem": "https://raw.githubusercontent.com/trezhywinks/API-Makima/main/IMG_4991.jpeg",
      "date": "2026-02-11"
    },
    {
      "id": 110570076,
      "name": "trezhywinks",
      "caregoria": "cosplay",
      "autor": "makima",
      "text": "Makima Cosplay",
      "creator": "https://github.com/trezhywinks",
      "github": "https://github.com/trezhywinks/API-Makima/",
      "imagem": "https://raw.githubusercontent.com/trezhywinks/API-Makima/main/IMG_4992.jpeg",
      "date": "2026-02-11"
    },
    {
      "id": 599040550,
      "name": "trezhywinks",
      "caregoria": "cosplay",
      "autor": "makima",
      "text": "Makima Cosplay",
      "creator": "https://github.com/trezhywinks",
      "github": "https://github.com/trezhywinks/API-Makima/",
      "imagem": "https://raw.githubusercontent.com/trezhywinks/API-Makima/main/IMG_4993.jpeg",
      "date": "2026-02-11"
    },
    {
      "id": 948555894,
      "name": "trezhywinks",
      "caregoria": "cosplay",
      "autor": "makima",
      "text": "Makima Cosplay",
      "creator": "https://github.com/trezhywinks",
      "github": "https://github.com/trezhywinks/API-Makima/",
      "imagem": "https://raw.githubusercontent.com/trezhywinks/API-Makima/main/IMG_4995.jpeg",
      "date": "2026-02-11"
    },
    {
      "id": 211633327,
      "name": "trezhywinks",
      "caregoria": "cosplay",
      "autor": "makima",
      "text": "Makima Cosplay",
      "creator": "https://github.com/trezhywinks",
      "github": "https://github.com/trezhywinks/API-Makima/",
      "imagem": "https://raw.githubusercontent.com/trezhywinks/API-Makima/main/IMG_4996.jpeg",
      "date": "2026-02-11"
    },
    {
      "id": 815423509,
      "name": "trezhywinks",
      "caregoria": "cosplay",
      "autor": "makima",
      "text": "Makima Cosplay",
      "creator": "https://github.com/trezhywinks",
      "github": "https://github.com/trezhywinks/API-Makima/",
      "imagem": "https://raw.githubusercontent.com/trezhywinks/API-Makima/main/IMG_4997.jpeg",
      "date": "2026-02-11"
    },
    {
      "id": 139338221,
      "name": "trezhywinks",
      "caregoria": "cosplay",
      "autor": "makima",
      "text": "Makima Cosplay",
      "creator": "https://github.com/trezhywinks",
      "github": "https://github.com/trezhywinks/API-Makima/",
      "imagem": "https://raw.githubusercontent.com/trezhywinks/API-Makima/main/IMG_4998.jpeg",
      "date": "2026-02-11"
    },
    {
      "id": 463183344,
      "name": "trezhywinks",
      "caregoria": "cosplay",
      "autor": "makima",
      "text": "Makima Cosplay",
      "creator": "https://github.com/trezhywinks",
      "github": "https://github.com/trezhywinks/API-Makima/",
      "imagem": "https://raw.githubusercontent.com/trezhywinks/API-Makima/main/IMG_4999.jpeg",
      "date": "2026-02-11"
    },
    {
      "id": 965143011,
      "name": "trezhywinks",
      "caregoria": "cosplay",
      "autor": "makima",
      "text": "Makima Cosplay",
      "creator": "https://github.com/trezhywinks",
      "github": "https://github.com/trezhywinks/API-Makima/",
      "imagem": "https://raw.githubusercontent.com/trezhywinks/API-Makima/main/IMG_5003.jpeg",
      "date": "2026-02-11"
    },
    {
      "id": 691488973,
      "name": "trezhywinks",
      "caregoria": "cosplay",
      "autor": "makima",
      "text": "Makima Cosplay",
      "creator": "https://github.com/trezhywinks",
      "github": "https://github.com/trezhywinks/API-Makima/",
      "imagem": "https://raw.githubusercontent.com/trezhywinks/API-Makima/main/IMG_5004.jpeg",
      "date": "2026-02-11"
    },
    {
      "id": 733672923,
      "name": "trezhywinks",
      "caregoria": "cosplay",
      "autor": "makima",
      "text": "Makima Cosplay",
      "creator": "https://github.com/trezhywinks",
      "github": "https://github.com/trezhywinks/API-Makima/",
      "imagem": "https://raw.githubusercontent.com/trezhywinks/API-Makima/main/IMG_5005.jpeg",
      "date": "2026-02-11"
    },
    {
      "id": 823607371,
      "name": "trezhywinks",
      "caregoria": "cosplay",
      "autor": "makima",
      "text": "Makima Cosplay",
      "creator": "https://github.com/trezhywinks",
      "github": "https://github.com/trezhywinks/API-Makima/",
      "imagem": "https://raw.githubusercontent.com/trezhywinks/API-Makima/main/IMG_5006.jpeg",
      "date": "2026-02-11"
    },
    {
      "id": 174262779,
      "name": "trezhywinks",
      "caregoria": "cosplay",
      "autor": "makima",
      "text": "Makima Cosplay",
      "creator": "https://github.com/trezhywinks",
      "github": "https://github.com/trezhywinks/API-Makima/",
      "imagem": "https://raw.githubusercontent.com/trezhywinks/API-Makima/main/IMG_5007.jpeg",
      "date": "2026-02-11"
    },
    {
      "id": 670606015,
      "name": "trezhywinks",
      "caregoria": "cosplay",
      "autor": "makima",
      "text": "Makima Cosplay",
      "creator": "https://github.com/trezhywinks",
      "github": "https://github.com/trezhywinks/API-Makima/",
      "imagem": "https://raw.githubusercontent.com/trezhywinks/API-Makima/main/IMG_5008.jpeg",
      "date": "2026-02-11"
    },
    {
      "id": 248816373,
      "name": "trezhywinks",
      "caregoria": "cosplay",
      "autor": "makima",
      "text": "Makima Cosplay",
      "creator": "https://github.com/trezhywinks",
      "github": "https://github.com/trezhywinks/API-Makima/",
      "imagem": "https://raw.githubusercontent.com/trezhywinks/API-Makima/main/IMG_5009.jpeg",
      "date": "2026-02-11"
    },
    {
      "id": 588035312,
      "name": "trezhywinks",
      "caregoria": "cosplay",
      "autor": "makima",
      "text": "Makima Cosplay",
      "creator": "https://github.com/trezhywinks",
      "github": "https://github.com/trezhywinks/API-Makima/",
      "imagem": "https://raw.githubusercontent.com/trezhywinks/API-Makima/main/IMG_5010.jpeg",
      "date": "2026-02-11"
    },
    {
      "id": 287901016,
      "name": "trezhywinks",
      "caregoria": "cosplay",
      "autor": "makima",
      "text": "Makima Cosplay",
      "creator": "https://github.com/trezhywinks",
      "github": "https://github.com/trezhywinks/API-Makima/",
      "imagem": "https://raw.githubusercontent.com/trezhywinks/API-Makima/main/IMG_5011.jpeg",
      "date": "2026-02-11"
    },
    {
      "id": 462102236,
      "name": "trezhywinks",
      "caregoria": "cosplay",
      "autor": "makima",
      "text": "Makima Cosplay",
      "creator": "https://github.com/trezhywinks",
      "github": "https://github.com/trezhywinks/API-Makima/",
      "imagem": "https://raw.githubusercontent.com/trezhywinks/API-Makima/main/IMG_5012.jpeg",
      "date": "2026-02-11"
    },
    {
      "id": 436747152,
      "name": "trezhywinks",
      "caregoria": "cosplay",
      "autor": "makima",
      "text": "Makima Cosplay",
      "creator": "https://github.com/trezhywinks",
      "github": "https://github.com/trezhywinks/API-Makima/",
      "imagem": "https://raw.githubusercontent.com/trezhywinks/API-Makima/main/IMG_5013.jpeg",
      "date": "2026-02-11"
    },
    {
      "id": 488716467,
      "name": "trezhywinks",
      "caregoria": "cosplay",
      "autor": "makima",
      "text": "Makima Cosplay",
      "creator": "https://github.com/trezhywinks",
      "github": "https://github.com/trezhywinks/API-Makima/",
      "imagem": "https://raw.githubusercontent.com/trezhywinks/API-Makima/main/IMG_5014.jpeg",
      "date": "2026-02-11"
    },
    {
      "id": 621840477,
      "name": "trezhywinks",
      "caregoria": "cosplay",
      "autor": "makima",
      "text": "Makima Cosplay",
      "creator": "https://github.com/trezhywinks",
      "github": "https://github.com/trezhywinks/API-Makima/",
      "imagem": "https://raw.githubusercontent.com/trezhywinks/API-Makima/main/IMG_5039.jpeg",
      "date": "2026-02-11"
    },
    {
      "id": 863228138,
      "name": "trezhywinks",
      "caregoria": "cosplay",
      "autor": "makima",
      "text": "Makima Cosplay",
      "creator": "https://github.com/trezhywinks",
      "github": "https://github.com/trezhywinks/API-Makima/",
      "imagem": "https://raw.githubusercontent.com/trezhywinks/API-Makima/main/IMG_5055.jpeg",
      "date": "2026-02-11"
    },
    {
      "id": 902459510,
      "name": "trezhywinks",
      "caregoria": "cosplay",
      "autor": "makima",
      "text": "Makima Cosplay",
      "creator": "https://github.com/trezhywinks",
      "github": "https://github.com/trezhywinks/API-Makima/",
      "imagem": "https://raw.githubusercontent.com/trezhywinks/API-Makima/main/IMG_5056.jpeg",
      "date": "2026-02-11"
    },
    {
      "id": 309922545,
      "name": "trezhywinks",
      "caregoria": "cosplay",
      "autor": "makima",
      "text": "Makima Cosplay",
      "creator": "https://github.com/trezhywinks",
      "github": "https://github.com/trezhywinks/API-Makima/",
      "imagem": "https://raw.githubusercontent.com/trezhywinks/API-Makima/main/IMG_5057.jpeg",
      "date": "2026-02-11"
    },
    {
      "id": 895956574,
      "name": "trezhywinks",
      "caregoria": "cosplay",
      "autor": "makima",
      "text": "Makima Cosplay",
      "creator": "https://github.com/trezhywinks",
      "github": "https://github.com/trezhywinks/API-Makima/",
      "imagem": "https://raw.githubusercontent.com/trezhywinks/API-Makima/main/IMG_5058.jpeg",
      "date": "2026-02-11"
    },
    {
      "id": 126109683,
      "name": "trezhywinks",
      "caregoria": "cosplay",
      "autor": "makima",
      "text": "Makima Cosplay",
      "creator": "https://github.com/trezhywinks",
      "github": "https://github.com/trezhywinks/API-Makima/",
      "imagem": "https://raw.githubusercontent.com/trezhywinks/API-Makima/main/IMG_5059.jpeg",
      "date": "2026-02-11"
    },
    {
      "id": 471787790,
      "name": "trezhywinks",
      "caregoria": "cosplay",
      "autor": "makima",
      "text": "Makima Cosplay",
      "creator": "https://github.com/trezhywinks",
      "github": "https://github.com/trezhywinks/API-Makima/",
      "imagem": "https://raw.githubusercontent.com/trezhywinks/API-Makima/main/IMG_5060.jpeg",
      "date": "2026-02-11"
    },
    {
      "id": 643886796,
      "name": "trezhywinks",
      "caregoria": "cosplay",
      "autor": "makima",
      "text": "Makima Cosplay",
      "creator": "https://github.com/trezhywinks",
      "github": "https://github.com/trezhywinks/API-Makima/",
      "imagem": "https://raw.githubusercontent.com/trezhywinks/API-Makima/main/IMG_5061.jpeg",
      "date": "2026-02-11"
    },
    {
      "id": 391209701,
      "name": "trezhywinks",
      "caregoria": "cosplay",
      "autor": "makima",
      "text": "Makima Cosplay",
      "creator": "https://github.com/trezhywinks",
      "github": "https://github.com/trezhywinks/API-Makima/",
      "imagem": "https://raw.githubusercontent.com/trezhywinks/API-Makima/main/IMG_5062.jpeg",
      "date": "2026-02-11"
    },
    {
      "id": 180035472,
      "name": "trezhywinks",
      "caregoria": "cosplay",
      "autor": "makima",
      "text": "Makima Cosplay",
      "creator": "https://github.com/trezhywinks",
      "github": "https://github.com/trezhywinks/API-Makima/",
      "imagem": "https://raw.githubusercontent.com/trezhywinks/API-Makima/main/IMG_5063.jpeg",
      "date": "2026-02-11"
    },
    {
      "id": 215132201,
      "name": "trezhywinks",
      "caregoria": "cosplay",
      "autor": "makima",
      "text": "Makima Cosplay",
      "creator": "https://github.com/trezhywinks",
      "github": "https://github.com/trezhywinks/API-Makima/",
      "imagem": "https://raw.githubusercontent.com/trezhywinks/API-Makima/main/IMG_5078.jpeg",
      "date": "2026-02-11"
    },
    {
      "id": 565553223,
      "name": "trezhywinks",
      "caregoria": "cosplay",
      "autor": "makima",
      "text": "Makima Cosplay",
      "creator": "https://github.com/trezhywinks",
      "github": "https://github.com/trezhywinks/API-Makima/",
      "imagem": "https://raw.githubusercontent.com/trezhywinks/API-Makima/main/IMG_5079.jpeg",
      "date": "2026-02-11"
    },
    {
      "id": 355192689,
      "name": "trezhywinks",
      "caregoria": "cosplay",
      "autor": "makima",
      "text": "Makima Cosplay",
      "creator": "https://github.com/trezhywinks",
      "github": "https://github.com/trezhywinks/API-Makima/",
      "imagem": "https://raw.githubusercontent.com/trezhywinks/API-Makima/main/IMG_5080.jpeg",
      "date": "2026-02-11"
    },
    {
      "id": 317589279,
      "name": "trezhywinks",
      "caregoria": "cosplay",
      "autor": "makima",
      "text": "Makima Cosplay",
      "creator": "https://github.com/trezhywinks",
      "github": "https://github.com/trezhywinks/API-Makima/",
      "imagem": "https://raw.githubusercontent.com/trezhywinks/API-Makima/main/IMG_5082.jpeg",
      "date": "2026-02-11"
    },
    {
      "id": 249167430,
      "name": "trezhywinks",
      "caregoria": "cosplay",
      "autor": "makima",
      "text": "Makima Cosplay",
      "creator": "https://github.com/trezhywinks",
      "github": "https://github.com/trezhywinks/API-Makima/",
      "imagem": "https://raw.githubusercontent.com/trezhywinks/API-Makima/main/IMG_5083.jpeg",
      "date": "2026-02-11"
    },
    {
      "id": 302865379,
      "name": "trezhywinks",
      "caregoria": "cosplay",
      "autor": "makima",
      "text": "Makima Cosplay",
      "creator": "https://github.com/trezhywinks",
      "github": "https://github.com/trezhywinks/API-Makima/",
      "imagem": "https://raw.githubusercontent.com/trezhywinks/API-Makima/main/IMG_5088.jpeg",
      "date": "2026-02-11"
    },
    {
      "id": 122502775,
      "name": "trezhywinks",
      "caregoria": "cosplay",
      "autor": "makima",
      "text": "Makima Cosplay",
      "creator": "https://github.com/trezhywinks",
      "github": "https://github.com/trezhywinks/API-Makima/",
      "imagem": "https://raw.githubusercontent.com/trezhywinks/API-Makima/main/IMG_5089.jpeg",
      "date": "2026-02-11"
    },
    {
      "id": 463699956,
      "name": "trezhywinks",
      "caregoria": "cosplay",
      "autor": "makima",
      "text": "Makima Cosplay",
      "creator": "https://github.com/trezhywinks",
      "github": "https://github.com/trezhywinks/API-Makima/",
      "imagem": "https://raw.githubusercontent.com/trezhywinks/API-Makima/main/IMG_5092.jpeg",
      "date": "2026-02-11"
    },
    {
      "id": 530521367,
      "name": "trezhywinks",
      "caregoria": "cosplay",
      "autor": "makima",
      "text": "Makima Cosplay",
      "creator": "https://github.com/trezhywinks",
      "github": "https://github.com/trezhywinks/API-Makima/",
      "imagem": "https://raw.githubusercontent.com/trezhywinks/API-Makima/main/IMG_5093.jpeg",
      "date": "2026-02-11"
    },
    {
      "id": 877923188,
      "name": "trezhywinks",
      "caregoria": "cosplay",
      "autor": "makima",
      "text": "Makima Cosplay",
      "creator": "https://github.com/trezhywinks",
      "github": "https://github.com/trezhywinks/API-Makima/",
      "imagem": "https://raw.githubusercontent.com/trezhywinks/API-Makima/main/IMG_5095.jpeg",
      "date": "2026-02-11"
    }
  ]
}